bda.plone.stripe-1.0-py3.9-nspkg.pth
bda/plone/stripe/__init__.py
bda/plone/stripe/checkout.pt
bda/plone/stripe/configure.zcml
bda/plone/stripe/failed.pt
bda/plone/stripe/i18n.sh
bda/plone/stripe/interfaces.py
bda/plone/stripe/success.pt
bda/plone/stripe/locales/bda.plone.stripe.pot
bda/plone/stripe/locales/de/LC_MESSAGES/bda.plone.stripe.po
bda/plone/stripe/locales/en/LC_MESSAGES/bda.plone.stripe.po
bda/plone/stripe/locales/fr/LC_MESSAGES/bda.plone.stripe.po
bda/plone/stripe/locales/it/LC_MESSAGES/bda.plone.stripe.po
bda/plone/stripe/locales/nl/LC_MESSAGES/bda.plone.stripe.po
bda/plone/stripe/locales/no/LC_MESSAGES/bda.plone.stripe.po
bda/plone/stripe/profile/metadata.xml
bda/plone/stripe/profile/registry.xml
bda.plone.stripe-1.0.dist-info/LICENSE.rst
bda.plone.stripe-1.0.dist-info/LICENSE_GPL.rst
bda.plone.stripe-1.0.dist-info/METADATA
bda.plone.stripe-1.0.dist-info/WHEEL
bda.plone.stripe-1.0.dist-info/entry_points.txt
bda.plone.stripe-1.0.dist-info/namespace_packages.txt
bda.plone.stripe-1.0.dist-info/top_level.txt
bda.plone.stripe-1.0.dist-info/RECORD
